CANoe_Python/CANoe.py
CANoe_Python/__init__.py
CANoe_Python/__main__.py
CANoe_Python/Application/Application.py
CANoe_Python/Application/__init__.py
CANoe_Python/Application/Bus/Bus.py
CANoe_Python/Application/Bus/__init__.py
CANoe_Python/Application/CAPL/CAPL.py
CANoe_Python/Application/CAPL/__init__.py
CANoe_Python/Application/Environment/Environment.py
CANoe_Python/Application/Environment/__init__.py
CANoe_Python/Application/Measurement/Measurement.py
CANoe_Python/Application/Measurement/__init__.py
CANoe_Python/Application/System/System.py
CANoe_Python/Application/System/__init__.py
CANoe_Python/Application/System/Namespaces/Namespaces.py
CANoe_Python/Application/System/Namespaces/__init__.py
CANoe_Python/Application/System/Namespaces/Namespace/Namespace.py
CANoe_Python/Application/System/Namespaces/Namespace/__init__.py
CANoe_Python-0.0.2.dist-info/LICENSE
CANoe_Python-0.0.2.dist-info/METADATA
CANoe_Python-0.0.2.dist-info/WHEEL
CANoe_Python-0.0.2.dist-info/top_level.txt
CANoe_Python-0.0.2.dist-info/RECORD
