Metadata-Version: 2.1
Name: CANoe-Python
Version: 0.0.2
Summary: CANoe COM Interface Python API
Home-page: https://github.com/claudiualbu/CANoe_Python
Author: Claudiu Albu
Author-email: claudiu.albu@hotmail.com
License: UNKNOWN
Platform: UNKNOWN
Classifier: Programming Language :: Python :: 3
Classifier: License :: OSI Approved :: MIT License
Classifier: Operating System :: OS Independent
